trayscope/__init__.py
trayscope/config.py
trayscope/main.py
trayscope/process.py
trayscope/tray.py
trayscope/icons/trayscope-active.svg
trayscope/icons/trayscope-inactive.svg
trayscope/icons/trayscope.svg
trayscope-0.3.1.dist-info/licenses/LICENSE
trayscope-0.3.1.dist-info/METADATA
trayscope-0.3.1.dist-info/WHEEL
trayscope-0.3.1.dist-info/entry_points.txt
trayscope-0.3.1.dist-info/top_level.txt
trayscope-0.3.1.dist-info/RECORD
