Metadata-Version: 2.4
Name: trayscope
Version: 0.3.1
Summary: System tray application for managing gamescope
Author: Omnimodular AB
License-Expression: BSD-2-Clause
Project-URL: Homepage, https://github.com/omnimodular/trayscope
Project-URL: Repository, https://github.com/omnimodular/trayscope
Project-URL: Issues, https://github.com/omnimodular/trayscope/issues
Keywords: gamescope,steam,gaming,wayland,compositor,tray
Classifier: Development Status :: 4 - Beta
Classifier: Environment :: X11 Applications :: GTK
Classifier: Intended Audience :: End Users/Desktop
Classifier: Operating System :: POSIX :: Linux
Classifier: Programming Language :: Python :: 3
Classifier: Programming Language :: Python :: 3.10
Classifier: Programming Language :: Python :: 3.11
Classifier: Programming Language :: Python :: 3.12
Classifier: Topic :: Games/Entertainment
Classifier: Topic :: Desktop Environment
Requires-Python: >=3.10
License-File: LICENSE
Requires-Dist: dbus-next>=0.2.3
Dynamic: license-file
